yakusoku/__init__.py
yakusoku/context.py
yakusoku/coroutines.py
yakusoku/future.py
yakusoku/operations.py
yakusoku/typings.py
yakusoku-1.0.0.dist-info/METADATA
yakusoku-1.0.0.dist-info/RECORD
yakusoku-1.0.0.dist-info/WHEEL
yakusoku-1.0.0.dist-info/top_level.txt
