Metadata-Version: 2.1
Name: yakusoku
Version: 1.0.0
Summary: A unified Future for Threading and AsyncIO
Home-page: https://github.com/stuxcrystal/yakusoku
Author: stuxcrystal
Author-email: stuxcrystal@encode.moe
License: Apache License
Platform: UNKNOWN
Classifier: Development Status :: 4 - Beta
Classifier: License :: OSI Approved :: Apache Software License
Classifier: Programming Language :: Python :: 3.6
Classifier: Framework :: AsyncIO
Classifier: Intended Audience :: Developers
